{"data": {"amount": 1144866842.0, "revenue": 1144866842.0, "expense": 0.0}, "key": "Budget", "values": [{"data": {"amount": 589064333.0, "revenue": 589064333.0, "expense": 0.0}, "key": "Governmental Funds", "values": [{"data": {"amount": 30224040.0, "revenue": 30224040.0, "expense": 0.0}, "key": "Licenses and Permits"}, {"data": {"amount": 430263042.0, "revenue": 430263042.0, "expense": 0.0}, "key": "Taxes"}, {"data": {"amount": 14385988.0, "revenue": 14385988.0, "expense": 0.0}, "key": "Intergovernmental"}, {"data": {"amount": 67123064.0, "revenue": 67123064.0, "expense": 0.0}, "key": "Charges, Fees, and Services"}, {"data": {"amount": 654000.0, "revenue": 654000.0, "expense": 0.0}, "key": "Interest, Rents, and Concessions"}, {"data": {"amount": 36912700.0, "revenue": 36912700.0, "expense": 0.0}, "key": "Contributions from Other Funds"}, {"data": {"amount": 8991367.0, "revenue": 8991367.0, "expense": 0.0}, "key": "Fines, Forfeitures, and  Penalties"}, {"data": {"amount": 510132.0, "revenue": 510132.0, "expense": 0.0}, "key": "Miscellaneous Revenue"}]}, {"data": {"amount": 126147519.0, "revenue": 126147519.0, "expense": 0.0}, "key": "Other Governmental Funds", "values": [{"data": {"amount": 25654377.0, "revenue": 25654377.0, "expense": 0.0}, "key": "Intergovernmental"}, {"data": {"amount": 60794197.0, "revenue": 60794197.0, "expense": 0.0}, "key": "Charges, Fees, and Services"}, {"data": {"amount": 7031600.0, "revenue": 7031600.0, "expense": 0.0}, "key": "Interest, Rents, and Concessions"}, {"data": {"amount": 26087901.0, "revenue": 26087901.0, "expense": 0.0}, "key": "Taxes"}, {"data": {"amount": 342900.0, "revenue": 342900.0, "expense": 0.0}, "key": "Miscellaneous Revenue"}, {"data": {"amount": 5836544.0, "revenue": 5836544.0, "expense": 0.0}, "key": "Licenses and Permits"}, {"data": {"amount": 400000.0, "revenue": 400000.0, "expense": 0.0}, "key": "Fines, Forfeitures, and  Penalties"}]}, {"data": {"amount": 329402081.0, "revenue": 329402081.0, "expense": 0.0}, "key": "Enterprise Funds", "values": [{"data": {"amount": 311413678.0, "revenue": 311413678.0, "expense": 0.0}, "key": "Charges, Fees, and Services"}, {"data": {"amount": 3100.0, "revenue": 3100.0, "expense": 0.0}, "key": "Fines, Forfeitures, and  Penalties"}, {"data": {"amount": 3297754.0, "revenue": 3297754.0, "expense": 0.0}, "key": "Interest, Rents, and Concessions"}, {"data": {"amount": 1054500.0, "revenue": 1054500.0, "expense": 0.0}, "key": "Intergovernmental"}, {"data": {"amount": 866000.0, "revenue": 866000.0, "expense": 0.0}, "key": "Miscellaneous Revenue"}, {"data": {"amount": 12672049.0, "revenue": 12672049.0, "expense": 0.0}, "key": "Taxes"}, {"data": {"amount": 95000.0, "revenue": 95000.0, "expense": 0.0}, "key": "Licenses and Permits"}]}, {"data": {"amount": 45820000.0, "revenue": 45820000.0, "expense": 0.0}, "key": "Risk Management", "values": [{"data": {"amount": 571000.0, "revenue": 571000.0, "expense": 0.0}, "key": "Interest, Rents, and Concessions"}, {"data": {"amount": 350000.0, "revenue": 350000.0, "expense": 0.0}, "key": "Charges, Fees, and Services"}, {"data": {"amount": 44899000.0, "revenue": 44899000.0, "expense": 0.0}, "key": "Miscellaneous Revenue"}]}, {"data": {"amount": 54432909.0, "revenue": 54432909.0, "expense": 0.0}, "key": "Internal Service Funds", "values": [{"data": {"amount": 7657338.0, "revenue": 7657338.0, "expense": 0.0}, "key": "Charges, Fees, and Services"}, {"data": {"amount": 511254.0, "revenue": 511254.0, "expense": 0.0}, "key": "Interest, Rents, and Concessions"}, {"data": {"amount": 46264317.0, "revenue": 46264317.0, "expense": 0.0}, "key": "Miscellaneous Revenue"}]}]}