[{"budget_type": "1", "fiscal_year_range": 2019, "account_category": "Charges, Fees, and Services", "total": "425692408", "general_fund": "61754822"}, {"budget_type": "1", "fiscal_year_range": 2019, "account_category": "Contributions from Other Funds", "total": "35043458", "general_fund": "35043458"}, {"budget_type": "1", "fiscal_year_range": 2019, "account_category": "Fines, Forfeitures, and  Penalties", "total": "14046003", "general_fund": "13542903"}, {"budget_type": "1", "fiscal_year_range": 2019, "account_category": "Interest, Rents, and Concessions", "total": "16166123", "general_fund": "654000"}, {"budget_type": "1", "fiscal_year_range": 2019, "account_category": "Intergovernmental", "total": "32076074", "general_fund": "13375758"}, {"budget_type": "1", "fiscal_year_range": 2019, "account_category": "Licenses and Permits", "total": "32263744", "general_fund": "28664697"}, {"budget_type": "1", "fiscal_year_range": 2019, "account_category": "Miscellaneous Revenue", "total": "75962235", "general_fund": "510132"}, {"budget_type": "1", "fiscal_year_range": 2019, "account_category": "Taxes", "total": "419635463", "general_fund": "340003230"}]